setup.py
hotreloader/__init__.py
hotreloader/database.py
hotreloader/example.py
hotreloader/models.py
hotreloader/setup.py
hotreloader/triggers.py
hotreloader/utils.py
hotreloader/worker.py
hotreloader.egg-info/PKG-INFO
hotreloader.egg-info/SOURCES.txt
hotreloader.egg-info/dependency_links.txt
hotreloader.egg-info/top_level.txt
hotreloader/MentoDB/__init__.py
hotreloader/MentoDB/connection.py
hotreloader/MentoDB/models.py
hotreloader/MentoDB/plugins.py
hotreloader/MentoDB/tests.py
hotreloader/MentoDB/utils.py