Metadata-Version: 2.1
Name: hotreloader
Version: 0.2.2
Summary: A hot-reload framework can watch files and handle it when file is edited.
Home-page: https://github.com/fswair/PyReloader
Author: Mert Sırakaya
Author-email: usirakaya@ogr.iu.edu.tr
Keywords: hot-reload,file-watching,reloader
Requires: pandas
Requires: numpy
Requires: pydantic
